CHANGELOG.md
CONTRIBUTING.md
LICENSE
MANIFEST.in
Makefile
README.md
mkdocs.yml
requirements-dev.txt
requirements.txt
setup.cfg
setup.py
watson.completion
watson.zsh-completion
docs/faq.md
docs/index.md
docs/about/license.md
docs/about/release-notes.md
docs/contributing/coc.md
docs/contributing/hack.md
docs/contributing/how-to.md
docs/contributing/pr-guidelines.md
docs/contributing/release-new-version.md
docs/css/watson.css
docs/img/logo-watson-600px.png
docs/img/logo-watson.svg
docs/img/screenshot.png
docs/img/watson-demo.gif
docs/img/working-cat.gif
docs/user-guide/commands.md
docs/user-guide/configuration.md
scripts/create-completion-script.sh
scripts/fuzzer.py
scripts/gen-cli-docs.py
tests/__init__.py
tests/conftest.py
tests/test_autocompletion.py
tests/test_cli.py
tests/test_config.py
tests/test_fullmoon.py
tests/test_utils.py
tests/test_watson.py
tests/resources/frames-with-conflict
watson/__init__.py
watson/__main__.py
watson/autocompletion.py
watson/cli.py
watson/config.py
watson/frames.py
watson/fullmoon.py
watson/utils.py
watson/version.py
watson/watson.py
watson_next.egg-info/PKG-INFO
watson_next.egg-info/SOURCES.txt
watson_next.egg-info/dependency_links.txt
watson_next.egg-info/entry_points.txt
watson_next.egg-info/requires.txt
watson_next.egg-info/top_level.txt